{
    "section": "acecup",
    "shot_1": {
        "section": "cup-ap",
        "analysis_success": false,
        "analysis_error_code": null,
        "side": null,
        "imuangles": [
            0.0,
            0.0,
            0.0,
            20.0
        ],
        "landmarks": {
            "femur": [
                {
                    "colour": "F0E442",
                    "handle": [
                        425,
                        387
                    ],
                    "points": [
                        [
                            387,
                            679
                        ],
                        [
                            494,
                            601
                        ],
                        [
                            662,
                            589
                        ],
                        [
                            441,
                            521
                        ]
                    ],
                    "template": 0,
                    "type": "ellipse"
                }
            ],
            "pelvis": [
                {
                    "colour": "D55E00",
                    "handle": [
                        820,
                        568
                    ],
                    "points": [
                        [
                            723,
                            297
                        ],
                        [
                            727,
                            405
                        ],
                        [
                            753,
                            493
                        ],
                        [
                            822,
                            606
                        ],
                        [
                            905,
                            693
                        ]
                    ],
                    "template": 0,
                    "type": "lines"
                },
                {
                    "colour": "56B4E9",
                    "points": [
                        [
                            865,
                            761
                        ],
                        [
                            768,
                            813
                        ],
                        [
                            715,
                            757
                        ],
                        [
                            732,
                            665
                        ]
                    ],
                    "template": 0,
                    "type": "lines"
                },
                {
                    "colour": "CC79A7",
                    "points": [
                        [
                            757,
                            565
                        ]
                    ],
                    "template": 0,
                    "type": "lines"
                }
            ]
        },
        "analysis_parameters": {
            "extract_distortion": false,
            "correct_distortion": false,
            "extract_glyph": false,
            "extract_tracking": false,
            "extract_camcalib": false,
            "ai_mode": false
        },
        "framecalib": {},
        "ShotIndex": 4
    },
    "shot_2": {
        "section": "cup-ob",
        "analysis_success": false,
        "analysis_error_code": null,
        "side": null,
        "imuangles": [
            0.0,
            20.0,
            0.0,
            20.0
        ],
        "landmarks": {
            "femur": [
                {
                    "colour": "F0E442",
                    "handle": [
                        405,
                        450
                    ],
                    "points": [
                        [
                            400,
                            490
                        ],
                        [
                            524,
                            562
                        ],
                        [
                            614,
                            698
                        ],
                        [
                            569,
                            465
                        ]
                    ],
                    "template": 0,
                    "type": "ellipse"
                }
            ],
            "pelvis": [
                {
                    "colour": "D55E00",
                    "handle": [
                        830,
                        518
                    ],
                    "points": [
                        [
                            731,
                            247
                        ],
                        [
                            736,
                            355
                        ],
                        [
                            761,
                            443
                        ],
                        [
                            830,
                            556
                        ],
                        [
                            914,
                            643
                        ]
                    ],
                    "template": 0,
                    "type": "lines"
                },
                {
                    "colour": "56B4E9",
                    "points": [
                        [
                            873,
                            711
                        ],
                        [
                            776,
                            763
                        ],
                        [
                            724,
                            707
                        ],
                        [
                            741,
                            615
                        ]
                    ],
                    "template": 0,
                    "type": "lines"
                },
                {
                    "colour": "CC79A7",
                    "points": [
                        [
                            765,
                            515
                        ]
                    ],
                    "template": 0,
                    "type": "lines"
                }
            ]
        },
        "analysis_parameters": {
            "extract_distortion": false,
            "correct_distortion": false,
            "extract_glyph": false,
            "extract_tracking": false,
            "extract_camcalib": false,
            "ai_mode": false
        },
        "framecalib": {},
        "ShotIndex": 5
    },
    "analysis_success": true,
    "analysis_error_code": null,
    "recondata": 1,
    "ReconIndex": 2
}